aequilibrium/__init__.py
aequilibrium/balance.py
aequilibrium/dataset.py
aequilibrium/model.py
aequilibrium/results.py
aequilibrium/utils/__init__.py
aequilibrium/utils/api_wrapper.py
aequilibrium/visualize.py
aequilibrium-1.0.2.dist-info/LICENSE
aequilibrium-1.0.2.dist-info/WHEEL
aequilibrium-1.0.2.dist-info/METADATA
aequilibrium-1.0.2.dist-info/RECORD
